emailreminder/__init__.py
emailreminder/emailreminder.py
emailreminder-0.0.9.dist-info/LICENSE
emailreminder-0.0.9.dist-info/METADATA
emailreminder-0.0.9.dist-info/WHEEL
emailreminder-0.0.9.dist-info/top_level.txt
emailreminder-0.0.9.dist-info/RECORD
