Metadata-Version: 2.1
Name: emailreminder
Version: 0.0.9
Summary: A decorator
Home-page: https://github.com/Oswells/reminder.git
Author: Junjie Zhang
Author-email: zjunjie@hust.edu.cn
License: Apache License 2.0
Platform: UNKNOWN
License-File: LICENSE
Requires-Dist: requests
